swiggy_analytics/__init__.py
swiggy_analytics/cli.py
swiggy_analytics/constants.py
swiggy_analytics/db.py
swiggy_analytics/exceptions.py
swiggy_analytics/helper.py
swiggy_analytics/queries.py
swiggy_analytics/swiggy_analytics.py
swiggy_analytics/utils.py
swiggy_analytics-1.7.0.dist-info/LICENSE
swiggy_analytics-1.7.0.dist-info/METADATA
swiggy_analytics-1.7.0.dist-info/WHEEL
swiggy_analytics-1.7.0.dist-info/entry_points.txt
swiggy_analytics-1.7.0.dist-info/top_level.txt
swiggy_analytics-1.7.0.dist-info/RECORD
